{"BinanceU.ALPHAUSDT.perp":{"UP":{"client_order_id":"R48UP8jAdwcT","label":"UP","price":0.0816,"quantity":12255,"time":1737345603930},"DN":{"client_order_id":"R48DNLGtwzEN","label":"DN","price":0.0496,"quantity":20161,"time":1737345603931},"R48UP8jAdwcT":{"label":"UP","target":"SHORT","quantity":12255,"time":1737345603930,"filled":0},"R48DNLGtwzEN":{"label":"DN","target":"LONG","quantity":20161,"time":1737345603931,"filled":0}},"BinanceU.CHRUSDT.perp":{"UP":{"client_order_id":"R48UP8Y6mBsZ","label":"UP","price":0.2566,"quantity":3897,"time":1737216006185},"DN":{"client_order_id":"R48DNmTk4rDz","label":"DN","price":0.1588,"quantity":6297,"time":1737216006192},"R48UP8Y6mBsZ":{"label":"UP","target":"SHORT","quantity":3897,"time":1737216006185,"filled":0},"R48DNmTk4rDz":{"label":"DN","target":"LONG","quantity":6297,"time":1737216006192,"filled":0}}}