{"BinanceU.ETHUSDT.perp.1h":{"Q0101hUPotP08":{"label":"UP","target":"LONG","quantity":0.042,"time":1726145616303,"filled":0},"UP":{"client_order_id":"Q0101hUPotP08","label":"UP","stop_price":2397.12,"quantity":0.042,"time":1726145616303},"Q0101hUCR9sTS":{"label":"UC","target":"EMPTY","quantity":0.042,"time":1726145616306,"filled":0},"UC":{"client_order_id":"Q0101hUCR9sTS","label":"UC","price":2804.63,"quantity":0.042,"time":1726145616306},"Q0101hDNrrUnK":{"label":"DN","target":"SHORT","quantity":0.044,"time":1726145616307,"filled":0},"DN":{"client_order_id":"Q0101hDNrrUnK","label":"DN","stop_price":2297.76,"quantity":0.044,"time":1726145616307},"Q0101hDCW7vD2":{"label":"DC","target":"EMPTY","quantity":0.044,"time":1726145616307,"filled":0},"DC":{"client_order_id":"Q0101hDCW7vD2","label":"DC","price":1907.14,"quantity":0.044,"time":1726145616307}},"BinanceU.RUNEUSDT.perp.1h":{"Q0101hUP1rmIk":{"label":"UP","target":"LONG","quantity":25,"time":1726145616538,"filled":0},"UP":{"client_order_id":"Q0101hUP1rmIk","label":"UP","stop_price":3.96,"quantity":25,"time":1726145616538},"Q0101hUC6rLuT":{"label":"UC","target":"EMPTY","quantity":25,"time":1726145616539,"filled":0},"UC":{"client_order_id":"Q0101hUC6rLuT","label":"UC","price":4.752,"quantity":25,"time":1726145616539}}}