{"BinanceU.XEMUSDT.perp":{"ANTI_S":{"client_order_id":"R01SRw45yYQp","label":"ANTI_S|REVERSE","price":0.0285,"quantity":6969,"time":1688623200763},"R01SRw45yYQp":{"label":"ANTI_S|REVERSE","target":"LONG","quantity":6969,"time":1688623200763,"filled":0}},"BinanceU.ADAUSDT.perp":{"UP":{"client_order_id":"R01UPUeLiwnv","label":"UP","price":0.3002,"quantity":333,"time":1688623200309},"DN":{"client_order_id":"R01DNvrCtHAc","label":"DN","price":0.2718,"quantity":368,"time":1688623200309},"R01UPUeLiwnv":{"label":"UP","target":"SHORT","quantity":333,"time":1688623200309,"filled":0},"R01DNvrCtHAc":{"label":"DN","target":"LONG","quantity":368,"time":1688623200309,"filled":0}},"BinanceU.BANDUSDT.perp":{"UP":{"client_order_id":"R01UPxPmAzBZ","label":"UP","price":1.295,"quantity":77.2,"time":1688623200478},"DN":{"client_order_id":"R01DNZfKfbyR","label":"DN","price":1.2288,"quantity":81.4,"time":1688623200478},"R01UPxPmAzBZ":{"label":"UP","target":"SHORT","quantity":77.2,"time":1688623200478,"filled":0},"R01DNZfKfbyR":{"label":"DN","target":"LONG","quantity":81.4,"time":1688623200478,"filled":0}},"BinanceU.BNBUSDT.perp":{"UP":{"client_order_id":"R01UPVraKpXV","label":"UP","price":252.01,"quantity":0.4,"time":1688623200303},"DN":{"client_order_id":"R01DN6zWNfVr","label":"DN","price":230.41,"quantity":0.43,"time":1688623200303},"R01UPVraKpXV":{"label":"UP","target":"SHORT","quantity":0.4,"time":1688623200303,"filled":0},"R01DN6zWNfVr":{"label":"DN","target":"LONG","quantity":0.43,"time":1688623200303,"filled":0}},"BinanceU.CTKUSDT.perp":{"ANTI_L":{"client_order_id":"R01LS7dewI90","label":"ANTI_L|STOPLOSS","price":0.6258,"quantity":158,"time":1688623200454},"R01LS7dewI90":{"label":"ANTI_L|STOPLOSS","target":"EMPTY","quantity":158,"time":1688623200454,"filled":0}},"BinanceU.DYDXUSDT.perp":{"UP":{"client_order_id":"R01UPtmEJDzK","label":"UP","price":2.062,"quantity":48.5,"time":1688623200495},"DN":{"client_order_id":"R01DNSwTepEB","label":"DN","price":1.764,"quantity":56.7,"time":1688623200495},"R01UPtmEJDzK":{"label":"UP","target":"SHORT","quantity":48.5,"time":1688623200495,"filled":0},"R01DNSwTepEB":{"label":"DN","target":"LONG","quantity":56.7,"time":1688623200495,"filled":0}},"BinanceU.SKLUSDT.perp":{"UP":{"client_order_id":"R01UP4DIFJsJ","label":"UP","price":0.03005,"quantity":3328,"time":1688623201214},"DN":{"client_order_id":"R01DNR2AUNyf","label":"DN","price":0.02673,"quantity":3741,"time":1688623201214},"R01UP4DIFJsJ":{"label":"UP","target":"SHORT","quantity":3328,"time":1688623201214,"filled":0},"R01DNR2AUNyf":{"label":"DN","target":"LONG","quantity":3741,"time":1688623201214,"filled":0}},"BinanceU.SOLUSDT.perp":{"UP":{"client_order_id":"R01UP0tml3H0","label":"UP","price":20.95,"quantity":5,"time":1688623200233},"DN":{"client_order_id":"R01DNA1gil4B","label":"DN","price":18.07,"quantity":6,"time":1688623200233},"R01UP0tml3H0":{"label":"UP","target":"SHORT","quantity":5,"time":1688623200233,"filled":0},"R01DNA1gil4B":{"label":"DN","target":"LONG","quantity":6,"time":1688623200233,"filled":0}}}