{"BinanceU.BNBUSDT.perp":{"status":"EMPTY","anti_order_sent":false,"pos":0,"triggered":"","up":953.46,"dn":826.71,"long_enter":"","high_since_long":"","short_enter":"","low_since_short":"","bar_n":"","bar_enter_n":0,"ep":"","af":"","sar":"","stoploss_price":"","fee":0.073,"quote_ccy":-4.6,"net_profit":-4.67},"BinanceU.BATUSDT.perp":{"status":"EMPTY","anti_order_sent":false,"pos":0,"triggered":"","up":0.3235,"dn":0.2395,"long_enter":"","high_since_long":"","short_enter":"","low_since_short":"","bar_n":"","bar_enter_n":0,"ep":"","af":"","sar":"","stoploss_price":"","fee":0.082,"quote_ccy":2.76,"net_profit":2.68},"BinanceU.DASHUSDT.perp":{"status":"EMPTY","anti_order_sent":false,"pos":0,"triggered":"","up":56,"dn":35.74,"long_enter":"","high_since_long":"","short_enter":"","low_since_short":"","bar_n":"","bar_enter_n":0,"ep":"","af":"","sar":"","stoploss_price":"","fee":0,"quote_ccy":0,"net_profit":0},"BinanceU.DOGEUSDT.perp":{"status":"EMPTY","anti_order_sent":false,"pos":0,"triggered":"","up":0.14564,"dn":0.13102,"long_enter":"","high_since_long":"","short_enter":"","low_since_short":"","bar_n":"","bar_enter_n":0,"ep":"","af":"","sar":"","stoploss_price":"","fee":1.466,"quote_ccy":-15.42,"net_profit":-16.89},"BinanceU.KAVAUSDT.perp":{"status":"EMPTY","anti_order_sent":false,"pos":0,"triggered":"","up":0.1059,"dn":0.0841,"long_enter":"","high_since_long":"","short_enter":"","low_since_short":"","bar_n":"","bar_enter_n":0,"ep":"","af":"","sar":"","stoploss_price":"","fee":0.866,"quote_ccy":58.06,"net_profit":57.19},"BinanceU.NEARUSDT.perp":{"status":"EMPTY","anti_order_sent":false,"pos":0,"triggered":"","up":1.824,"dn":1.496,"long_enter":"","high_since_long":"","short_enter":"","low_since_short":"","bar_n":"","bar_enter_n":0,"ep":"","af":"","sar":"","stoploss_price":"","fee":0.091,"quote_ccy":-20.88,"net_profit":-20.97},"BinanceU.QTUMUSDT.perp":{"status":"EMPTY","anti_order_sent":false,"pos":0,"triggered":"","up":1.724,"dn":1.356,"long_enter":"","high_since_long":"","short_enter":"","low_since_short":"","bar_n":"","bar_enter_n":0,"ep":"","af":"","sar":"","stoploss_price":"","fee":0.175,"quote_ccy":2.86,"net_profit":2.69},"BinanceU.RLCUSDT.perp":{"status":"EMPTY","anti_order_sent":false,"pos":0,"triggered":"","up":0.7696,"dn":0.6834,"long_enter":"","high_since_long":"","short_enter":"","low_since_short":"","bar_n":"","bar_enter_n":0,"ep":"","af":"","sar":"","stoploss_price":"","fee":0.19,"quote_ccy":2.21,"net_profit":2.02},"BinanceU.SNXUSDT.perp":{"status":"EMPTY","anti_order_sent":false,"pos":0,"triggered":"","up":0.511,"dn":0.413,"long_enter":"","high_since_long":"","short_enter":"","low_since_short":"","bar_n":"","bar_enter_n":0,"ep":"","af":"","sar":"","stoploss_price":"","fee":0.188,"quote_ccy":0.66,"net_profit":0.47},"BinanceU.SOLUSDT.perp":{"status":"EMPTY","anti_order_sent":false,"pos":0,"triggered":"","up":143.01,"dn":123.95,"long_enter":"","high_since_long":"","short_enter":"","low_since_short":"","bar_n":"","bar_enter_n":0,"ep":"","af":"","sar":"","stoploss_price":"","fee":0.19,"quote_ccy":-7.86,"net_profit":-8.05},"BinanceU.VETUSDT.perp":{"status":"EMPTY","anti_order_sent":false,"pos":0,"triggered":"","up":0.012729,"dn":0.010748,"long_enter":"","high_since_long":"","short_enter":"","low_since_short":"","bar_n":"","bar_enter_n":0,"ep":"","af":"","sar":"","stoploss_price":"","fee":0.375,"quote_ccy":6.97,"net_profit":6.6},"BinanceU.XRPUSDT.perp":{"status":"EMPTY","anti_order_sent":false,"pos":0,"triggered":"","up":2.1306,"dn":1.9298,"long_enter":"","high_since_long":"","short_enter":"","low_since_short":"","bar_n":"","bar_enter_n":0,"ep":"","af":"","sar":"","stoploss_price":"","fee":0.094,"quote_ccy":-0.17,"net_profit":-0.26},"BinanceU.YFIUSDT.perp":{"status":"EMPTY","anti_order_sent":false,"pos":0,"triggered":"","up":3840,"dn":3298,"long_enter":"","high_since_long":"","short_enter":"","low_since_short":"","bar_n":"","bar_enter_n":0,"ep":"","af":"","sar":"","stoploss_price":"","fee":0.698,"quote_ccy":27.26,"net_profit":26.56}}