{"BinanceU.1000XECUSDT.perp.1h":{"status":"SHORT","pos":-1833,"real_pos":"","triggered":"","up":0.02848,"dn":0.02692,"enter":0.02728,"bar_n":3,"bar_enter_n":0,"ep":0.02697,"af":0.16,"sar":0.02911,"fee":0.04,"quote_ccy":49.85,"net_profit":-0.73},"BinanceU.1000SHIBUSDT.perp.1h":{"status":"EMPTY","pos":0,"real_pos":"","triggered":"","up":0.013526,"dn":0.013172,"enter":"","bar_n":"","bar_enter_n":0,"ep":"","af":"","sar":"","fee":12.04,"quote_ccy":-134.31,"net_profit":-146.35},"BinanceU.ALICEUSDT.perp.1h":{"status":"EMPTY","pos":0,"real_pos":"","triggered":"","up":1.034,"dn":0.954,"enter":"","bar_n":"","bar_enter_n":0,"ep":"","af":"","sar":"","fee":3.524,"quote_ccy":-126.81,"net_profit":-130.33},"BinanceU.BANDUSDT.perp.1h":{"status":"EMPTY","pos":0,"real_pos":"","triggered":"","up":1.1165,"dn":1.0649,"enter":"","bar_n":"","bar_enter_n":0,"ep":"","af":"","sar":"","fee":1.864,"quote_ccy":-19.41,"net_profit":-21.27},"BinanceU.HBARUSDT.perp.6h":{"status":"SHORT","pos":-4365,"real_pos":"","triggered":"","up":0.05185,"dn":0.04956,"enter":0.0504,"bar_n":3,"bar_enter_n":0,"ep":0.04897,"af":0.02,"sar":0.06971,"fee":10.021,"quote_ccy":195.97,"net_profit":-33.87},"BinanceU.ONTUSDT.perp.6h":{"status":"EMPTY","pos":0,"real_pos":"","triggered":"","up":0.1845,"dn":0.1551,"enter":"","bar_n":"","bar_enter_n":0,"ep":"","af":"","sar":"","fee":0.902,"quote_ccy":35.9,"net_profit":35},"BinanceU.NKNUSDT.perp.6h":{"status":"SHORT","pos":-3193,"real_pos":"","triggered":"","up":0.07408,"dn":0.06604,"enter":0.06891,"bar_n":8,"bar_enter_n":0,"ep":0.06585,"af":0.04,"sar":0.09678,"fee":5.522,"quote_ccy":-17.33,"net_profit":-242.47},"BinanceU.HOTUSDT.perp.12h":{"status":"EMPTY","pos":0,"real_pos":"","triggered":"","up":0.002309,"dn":0.00163,"enter":"","bar_n":"","bar_enter_n":0,"ep":"","af":"","sar":"","fee":0.458,"quote_ccy":-5.81,"net_profit":-6.27},"BinanceU.XEMUSDT.perp.1h":{"status":"EMPTY","pos":0,"real_pos":"","triggered":"","up":0.0484,"dn":0.0446,"enter":"","bar_n":"","bar_enter_n":0,"ep":"","af":"","sar":"","fee":1.171,"quote_ccy":-51.6,"net_profit":-52.77},"BinanceU.ANTUSDT.perp.1h":{"status":"EMPTY","pos":0,"real_pos":"","triggered":"","up":9.5,"dn":8.874,"enter":"","bar_n":"","bar_enter_n":0,"ep":"","af":"","sar":"","fee":0.728,"quote_ccy":47.8,"net_profit":47.07},"BinanceU.CTSIUSDT.perp.1h":{"status":"EMPTY","pos":0,"real_pos":"","triggered":"","up":0.1321,"dn":0.1257,"enter":"","bar_n":"","bar_enter_n":0,"ep":"","af":"","sar":"","fee":14.822,"quote_ccy":42.66,"net_profit":27.84},"BinanceU.XMRUSDT.perp.1h":{"status":"EMPTY","pos":0,"real_pos":"","triggered":"","up":174.7,"dn":165.66,"enter":"","bar_n":"","bar_enter_n":0,"ep":"","af":"","sar":"","fee":2.83,"quote_ccy":-36.5,"net_profit":-39.33},"BinanceU.STMXUSDT.perp.6h":{"status":"EMPTY","pos":0,"real_pos":"","triggered":"","up":0.00627,"dn":0.00563,"enter":"","bar_n":"","bar_enter_n":0,"ep":"","af":"","sar":"","fee":7.13,"quote_ccy":167.59,"net_profit":160.46},"BinanceU.ARPAUSDT.perp.6h":{"status":"EMPTY","pos":0,"real_pos":"","triggered":"","up":0.04871,"dn":0.03477,"enter":"","bar_n":"","bar_enter_n":0,"ep":"","af":"","sar":"","fee":2.631,"quote_ccy":2.82,"net_profit":0.19},"BinanceU.PEOPLEUSDT.perp.6h":{"status":"EMPTY","pos":0,"real_pos":"","triggered":"","up":0.06209,"dn":0.05497,"enter":"","bar_n":"","bar_enter_n":0,"ep":"","af":"","sar":"","fee":3.395,"quote_ccy":-12.87,"net_profit":-16.26},"BinanceU.ANKRUSDT.perp.6h":{"status":"SHORT","pos":-9224,"real_pos":"","triggered":"","up":0.02757,"dn":0.02289,"enter":0.02385,"bar_n":13,"bar_enter_n":0,"ep":0.02261,"af":0.01,"sar":0.02793,"fee":2.535,"quote_ccy":353.5,"net_profit":119.07},"BinanceU.C98USDT.perp.6h":{"status":"EMPTY","pos":0,"real_pos":"","triggered":"","up":0.1298,"dn":0.1069,"enter":"","bar_n":"","bar_enter_n":0,"ep":"","af":"","sar":"","fee":1.511,"quote_ccy":-13.67,"net_profit":-15.18},"BinanceU.MTLUSDT.perp.1d":{"status":"SHORT","pos":-236,"real_pos":"","triggered":"","up":0.994,"dn":0.8286,"enter":0.9318,"bar_n":1,"bar_enter_n":0,"ep":0.8736,"af":0.06,"sar":1.3977,"fee":1.238,"quote_ccy":147.62,"net_profit":-66.16},"BinanceU.ALPHAUSDT.perp.1d":{"status":"EMPTY","pos":0,"real_pos":"","triggered":"","up":0.0636,"dn":0.0485,"enter":"","bar_n":"","bar_enter_n":0,"ep":"","af":"","sar":"","fee":1.062,"quote_ccy":315.27,"net_profit":314.21},"BinanceU.DOGEUSDT.perp.1h":{"status":"EMPTY","pos":0,"real_pos":"","triggered":"","up":0.10573,"dn":0.09809,"enter":"","bar_n":"","bar_enter_n":0,"ep":"","af":"","sar":"","fee":3.522,"quote_ccy":-22.82,"net_profit":-26.34},"BinanceU.ENSUSDT.perp.1h":{"status":"SHORT","pos":-12.8,"real_pos":"","triggered":"","up":17.829,"dn":17.213,"enter":17.2,"bar_n":44,"bar_enter_n":0,"ep":16.563,"af":0.04,"sar":17.784,"fee":15.483,"quote_ccy":184.44,"net_profit":-53.62},"BinanceU.HOTUSDT.perp.6h":{"status":"SHORT","pos":-128280,"real_pos":"","triggered":"","up":0.00174,"dn":0.0015,"enter":0.001715,"bar_n":8,"bar_enter_n":0,"ep":0.001555,"af":0.18,"sar":0.001676,"fee":5.94,"quote_ccy":289.28,"net_profit":76.55},"BinanceU.ICXUSDT.perp.12h":{"status":"EMPTY","pos":0,"real_pos":"","triggered":"","up":0.1318,"dn":0.1212,"enter":"","bar_n":"","bar_enter_n":0,"ep":"","af":"","sar":"","fee":5.809,"quote_ccy":-133.93,"net_profit":-139.74},"BinanceU.ONTUSDT.perp.12h":{"status":"EMPTY","pos":0,"real_pos":"","triggered":"","up":0.1777,"dn":0.1653,"enter":"","bar_n":"","bar_enter_n":0,"ep":"","af":"","sar":"","fee":3.96,"quote_ccy":-131.81,"net_profit":-135.77},"BinanceU.BALUSDT.perp.1h":{"status":"EMPTY","pos":0,"real_pos":"","triggered":"","up":2.033,"dn":1.717,"enter":"","bar_n":"","bar_enter_n":0,"ep":"","af":"","sar":"","fee":2.454,"quote_ccy":-116.09,"net_profit":-118.54},"BinanceU.ETCUSDT.perp.1h":{"status":"EMPTY","pos":0,"real_pos":"","triggered":"","up":18.733,"dn":18.111,"enter":"","bar_n":"","bar_enter_n":0,"ep":"","af":"","sar":"","fee":6.233,"quote_ccy":-23.24,"net_profit":-29.47},"BinanceU.GRTUSDT.perp.1h":{"status":"EMPTY","pos":0,"real_pos":"","triggered":"","up":0.14686,"dn":0.1348,"enter":"","bar_n":"","bar_enter_n":0,"ep":"","af":"","sar":"","fee":2.362,"quote_ccy":91.69,"net_profit":89.33},"BinanceU.ICXUSDT.perp.1h":{"status":"EMPTY","pos":0,"real_pos":"","triggered":"","up":0.1307,"dn":0.1221,"enter":"","bar_n":"","bar_enter_n":0,"ep":"","af":"","sar":"","fee":1.033,"quote_ccy":-95.97,"net_profit":-97},"BinanceU.MKRUSDT.perp.1h":{"status":"EMPTY","pos":0,"real_pos":"","triggered":"","up":1688.9,"dn":1527.7,"enter":"","bar_n":"","bar_enter_n":0,"ep":"","af":"","sar":"","fee":4.118,"quote_ccy":86.83,"net_profit":82.71},"BinanceU.NKNUSDT.perp.1h":{"status":"SHORT","pos":-3246,"real_pos":"","triggered":"","up":0.07026,"dn":0.06822,"enter":0.06778,"bar_n":21,"bar_enter_n":0,"ep":0.06622,"af":0.02,"sar":0.08536,"fee":27.489,"quote_ccy":209.9,"net_profit":-40.85},"BinanceU.AXSUSDT.perp.12h":{"status":"EMPTY","pos":0,"real_pos":"","triggered":"","up":4.888,"dn":4.286,"enter":"","bar_n":"","bar_enter_n":0,"ep":"","af":"","sar":"","fee":1.477,"quote_ccy":113.13,"net_profit":111.65},"BinanceU.DGBUSDT.perp.1h":{"status":"EMPTY","pos":0,"real_pos":"","triggered":"","up":0.01696,"dn":0.0147,"enter":"","bar_n":"","bar_enter_n":0,"ep":"","af":"","sar":"","fee":0,"quote_ccy":0,"net_profit":0},"BinanceU.ALPHAUSDT.perp.6h":{"status":"EMPTY","pos":0,"real_pos":"","triggered":"","up":0.0621,"dn":0.0513,"enter":"","bar_n":"","bar_enter_n":0,"ep":"","af":"","sar":"","fee":0.918,"quote_ccy":27.46,"net_profit":26.54},"BinanceU.STMXUSDT.perp.12h":{"status":"EMPTY","pos":0,"real_pos":"","triggered":"","up":0.00625,"dn":0.00561,"enter":"","bar_n":"","bar_enter_n":0,"ep":"","af":"","sar":"","fee":4.911,"quote_ccy":-102.43,"net_profit":-107.34}}