{"BinanceU.1000XECUSDT.perp.1h":{"status":"SHORT","pos":-1833,"real_pos":"","triggered":"","up":0.02848,"dn":0.02692,"enter":0.02728,"bar_n":3,"bar_enter_n":0,"ep":0.02697,"af":0.16,"sar":0.02911,"fee":0.04,"quote_ccy":49.85,"net_profit":-0.73},"BinanceU.1000SHIBUSDT.perp.1h":{"status":"EMPTY","pos":0,"real_pos":"","triggered":"","up":0.016013,"dn":0.014785,"enter":"","bar_n":"","bar_enter_n":0,"ep":"","af":"","sar":"","fee":11.182,"quote_ccy":-141.96,"net_profit":-153.14},"BinanceU.ALICEUSDT.perp.1h":{"status":"EMPTY","pos":0,"real_pos":"","triggered":"","up":1.277,"dn":1.153,"enter":"","bar_n":"","bar_enter_n":0,"ep":"","af":"","sar":"","fee":3.524,"quote_ccy":-126.81,"net_profit":-130.33},"BinanceU.BANDUSDT.perp.1h":{"status":"EMPTY","pos":0,"real_pos":"","triggered":"","up":1.3651,"dn":1.1725,"enter":"","bar_n":"","bar_enter_n":0,"ep":"","af":"","sar":"","fee":1.864,"quote_ccy":-19.41,"net_profit":-21.27},"BinanceU.HBARUSDT.perp.6h":{"status":"EMPTY","pos":0,"real_pos":"","triggered":"","up":0.06129,"dn":0.05693,"enter":"","bar_n":"","bar_enter_n":0,"ep":"","af":"","sar":"","fee":9.366,"quote_ccy":-2.93,"net_profit":-12.3},"BinanceU.ONTUSDT.perp.6h":{"status":"EMPTY","pos":0,"real_pos":"","triggered":"","up":0.2237,"dn":0.1685,"enter":"","bar_n":"","bar_enter_n":0,"ep":"","af":"","sar":"","fee":0.902,"quote_ccy":35.9,"net_profit":35},"BinanceU.NKNUSDT.perp.6h":{"status":"SHORT","pos":-3394,"real_pos":"","triggered":"","up":0.08941,"dn":0.07579,"enter":0.06482,"bar_n":18,"bar_enter_n":0,"ep":0.06214,"af":0.01,"sar":0.09173,"fee":5.344,"quote_ccy":30.72,"net_profit":-270.89},"BinanceU.HOTUSDT.perp.12h":{"status":"EMPTY","pos":0,"real_pos":"","triggered":"","up":0.002309,"dn":0.00163,"enter":"","bar_n":"","bar_enter_n":0,"ep":"","af":"","sar":"","fee":0.458,"quote_ccy":-5.81,"net_profit":-6.27},"BinanceU.XEMUSDT.perp.1h":{"status":"EMPTY","pos":0,"real_pos":"","triggered":"","up":0.0484,"dn":0.0446,"enter":"","bar_n":"","bar_enter_n":0,"ep":"","af":"","sar":"","fee":1.171,"quote_ccy":-51.6,"net_profit":-52.77},"BinanceU.ANTUSDT.perp.1h":{"status":"EMPTY","pos":0,"real_pos":"","triggered":"","up":9.5,"dn":8.874,"enter":"","bar_n":"","bar_enter_n":0,"ep":"","af":"","sar":"","fee":0.728,"quote_ccy":47.8,"net_profit":47.07},"BinanceU.CTSIUSDT.perp.1h":{"status":"SHORT","pos":-1440,"real_pos":"","triggered":"","up":0.1574,"dn":0.1399,"enter":0.1528,"bar_n":3,"bar_enter_n":0,"ep":0.1458,"af":0.04,"sar":0.1551,"fee":13.958,"quote_ccy":254.22,"net_profit":25.27},"BinanceU.XMRUSDT.perp.1h":{"status":"EMPTY","pos":0,"real_pos":"","triggered":"","up":184.79,"dn":165.43,"enter":"","bar_n":"","bar_enter_n":0,"ep":"","af":"","sar":"","fee":2.83,"quote_ccy":-36.5,"net_profit":-39.33},"BinanceU.STMXUSDT.perp.6h":{"status":"SHORT","pos":-34921,"real_pos":"","triggered":"","up":0.00671,"dn":0.00599,"enter":0.0063,"bar_n":3,"bar_enter_n":0,"ep":0.00609,"af":0.02,"sar":0.0066,"fee":6.73,"quote_ccy":352.86,"net_profit":124.38},"BinanceU.ARPAUSDT.perp.6h":{"status":"EMPTY","pos":0,"real_pos":"","triggered":"","up":0.04843,"dn":0.03939,"enter":"","bar_n":"","bar_enter_n":0,"ep":"","af":"","sar":"","fee":2.473,"quote_ccy":11.32,"net_profit":8.85},"BinanceU.PEOPLEUSDT.perp.6h":{"status":"EMPTY","pos":0,"real_pos":"","triggered":"","up":0.08425,"dn":0.05533,"enter":"","bar_n":"","bar_enter_n":0,"ep":"","af":"","sar":"","fee":3.136,"quote_ccy":-28.91,"net_profit":-32.05},"BinanceU.ANKRUSDT.perp.6h":{"status":"EMPTY","pos":0,"real_pos":"","triggered":"","up":0.03066,"dn":0.02654,"enter":"","bar_n":"","bar_enter_n":0,"ep":"","af":"","sar":"","fee":2.491,"quote_ccy":133.51,"net_profit":131.02},"BinanceU.C98USDT.perp.6h":{"status":"EMPTY","pos":0,"real_pos":"","triggered":"","up":0.1599,"dn":0.1219,"enter":"","bar_n":"","bar_enter_n":0,"ep":"","af":"","sar":"","fee":1.511,"quote_ccy":-13.67,"net_profit":-15.18},"BinanceU.MTLUSDT.perp.1d":{"status":"EMPTY","pos":0,"real_pos":"","triggered":"","up":1.0955,"dn":0.9535,"enter":"","bar_n":"","bar_enter_n":0,"ep":"","af":"","sar":"","fee":1.194,"quote_ccy":-72.28,"net_profit":-73.47},"BinanceU.ALPHAUSDT.perp.1d":{"status":"EMPTY","pos":0,"real_pos":"","triggered":"","up":0.078,"dn":0.0545,"enter":"","bar_n":"","bar_enter_n":0,"ep":"","af":"","sar":"","fee":1.062,"quote_ccy":315.27,"net_profit":314.21},"BinanceU.DOGEUSDT.perp.1h":{"status":"EMPTY","pos":0,"real_pos":"","triggered":"","up":0.11961,"dn":0.10465,"enter":"","bar_n":"","bar_enter_n":0,"ep":"","af":"","sar":"","fee":2.751,"quote_ccy":-24.35,"net_profit":-27.1},"BinanceU.ENSUSDT.perp.1h":{"status":"SHORT","pos":-10.9,"real_pos":"","triggered":"","up":22.345,"dn":21.107,"enter":20.173,"bar_n":36,"bar_enter_n":0,"ep":19.819,"af":0.01,"sar":22.907,"fee":14.231,"quote_ccy":241.21,"net_profit":-10.89},"BinanceU.HOTUSDT.perp.6h":{"status":"EMPTY","pos":0,"real_pos":"","triggered":"","up":0.002644,"dn":0.0017,"enter":"","bar_n":"","bar_enter_n":0,"ep":"","af":"","sar":"","fee":5.59,"quote_ccy":73.6,"net_profit":68.01},"BinanceU.ICXUSDT.perp.12h":{"status":"EMPTY","pos":0,"real_pos":"","triggered":"","up":0.1601,"dn":0.1393,"enter":"","bar_n":"","bar_enter_n":0,"ep":"","af":"","sar":"","fee":5.66,"quote_ccy":-125.05,"net_profit":-130.71},"BinanceU.ONTUSDT.perp.12h":{"status":"EMPTY","pos":0,"real_pos":"","triggered":"","up":0.2039,"dn":0.1781,"enter":"","bar_n":"","bar_enter_n":0,"ep":"","af":"","sar":"","fee":3.96,"quote_ccy":-131.81,"net_profit":-135.77},"BinanceU.BALUSDT.perp.1h":{"status":"EMPTY","pos":0,"real_pos":"","triggered":"","up":2.313,"dn":2.064,"enter":"","bar_n":"","bar_enter_n":0,"ep":"","af":"","sar":"","fee":2.145,"quote_ccy":-107.49,"net_profit":-109.63},"BinanceU.ETCUSDT.perp.1h":{"status":"EMPTY","pos":0,"real_pos":"","triggered":"","up":21.044,"dn":20.02,"enter":"","bar_n":"","bar_enter_n":0,"ep":"","af":"","sar":"","fee":5.61,"quote_ccy":-36.58,"net_profit":-42.19},"BinanceU.GRTUSDT.perp.1h":{"status":"EMPTY","pos":0,"real_pos":"","triggered":"","up":0.18994,"dn":0.1566,"enter":"","bar_n":"","bar_enter_n":0,"ep":"","af":"","sar":"","fee":2.362,"quote_ccy":91.69,"net_profit":89.33},"BinanceU.ICXUSDT.perp.1h":{"status":"EMPTY","pos":0,"real_pos":"","triggered":"","up":0.1588,"dn":0.1404,"enter":"","bar_n":"","bar_enter_n":0,"ep":"","af":"","sar":"","fee":1.033,"quote_ccy":-95.97,"net_profit":-97},"BinanceU.MKRUSDT.perp.1h":{"status":"EMPTY","pos":0,"real_pos":"","triggered":"","up":2237.2,"dn":2006,"enter":"","bar_n":"","bar_enter_n":0,"ep":"","af":"","sar":"","fee":3.503,"quote_ccy":81.5,"net_profit":78},"BinanceU.NKNUSDT.perp.1h":{"status":"SHORT","pos":-2645,"real_pos":"","triggered":"","up":0.09064,"dn":0.08384,"enter":0.08319,"bar_n":17,"bar_enter_n":0,"ep":0.08091,"af":0.02,"sar":0.10664,"fee":25.817,"quote_ccy":255.44,"net_profit":-1.26},"BinanceU.AXSUSDT.perp.12h":{"status":"EMPTY","pos":0,"real_pos":"","triggered":"","up":5.878,"dn":4.668,"enter":"","bar_n":"","bar_enter_n":0,"ep":"","af":"","sar":"","fee":1.477,"quote_ccy":113.13,"net_profit":111.65},"BinanceU.DGBUSDT.perp.1h":{"status":"EMPTY","pos":0,"real_pos":"","triggered":"","up":0.01696,"dn":0.0147,"enter":"","bar_n":"","bar_enter_n":0,"ep":"","af":"","sar":"","fee":0,"quote_ccy":0,"net_profit":0},"BinanceU.ALPHAUSDT.perp.6h":{"status":"SHORT","pos":-3819,"real_pos":"","triggered":"","up":0.0731,"dn":0.0563,"enter":0.0576,"bar_n":24,"bar_enter_n":0,"ep":0.05434,"af":0.02,"sar":0.0746,"fee":0.808,"quote_ccy":246.95,"net_profit":-8.32},"BinanceU.STMXUSDT.perp.12h":{"status":"SHORT","pos":-35200,"real_pos":"","triggered":"","up":0.00672,"dn":0.006,"enter":0.00625,"bar_n":2,"bar_enter_n":0,"ep":0.00596,"af":0.02,"sar":0.00655,"fee":4.622,"quote_ccy":58.93,"net_profit":-169.21}}