{"BinanceU.XMRUSDT.perp":{"status":"SHORT","anti_order_sent":false,"pos":-5.045,"triggered":"","up":206.49,"dn":201.33,"long_enter":198.2,"high_since_long":205.5,"short_enter":"","low_since_short":"","bar_n":14,"bar_enter_n":0,"ep":205.5,"af":0.1,"sar":200.87,"stoploss_price":200.87,"fee":11.387,"quote_ccy":969.52,"net_profit":-65.19},"BinanceU.ANIMEUSDT.perp":{"status":"LONG","anti_order_sent":false,"pos":7092,"triggered":"","up":0.0143,"dn":0.0141,"long_enter":"","high_since_long":"","short_enter":0.0141,"low_since_short":0.014,"bar_n":1,"bar_enter_n":0,"ep":0.014,"af":0.02,"sar":0.0148,"stoploss_price":0.0147,"fee":2.488,"quote_ccy":-89.7,"net_profit":7.81},"BinanceU.CRVUSDT.perp":{"status":"SHORT","anti_order_sent":false,"pos":-196.1,"triggered":"","up":0.51,"dn":0.506,"long_enter":0.51,"high_since_long":0.511,"short_enter":"","low_since_short":"","bar_n":0,"bar_enter_n":1,"ep":0.511,"af":0.02,"sar":0.49,"stoploss_price":0.491,"fee":4.374,"quote_ccy":112.76,"net_profit":9.36},"BinanceU.XTZUSDT.perp":{"status":"LONG","anti_order_sent":false,"pos":165.8,"triggered":"","up":0.589,"dn":0.571,"long_enter":"","high_since_long":"","short_enter":0.603,"low_since_short":0.572,"bar_n":13,"bar_enter_n":0,"ep":0.576,"af":0.14,"sar":0.598,"stoploss_price":0.595,"fee":1.734,"quote_ccy":-144.55,"net_profit":-51.11},"BinanceU.CELOUSDT.perp":{"status":"LONG","anti_order_sent":false,"pos":346,"triggered":"","up":0.291,"dn":0.289,"long_enter":"","high_since_long":"","short_enter":0.289,"low_since_short":0.288,"bar_n":0,"bar_enter_n":1,"ep":0.288,"af":0.02,"sar":0.303,"stoploss_price":0.302,"fee":2.594,"quote_ccy":-95.9,"net_profit":1.5},"BinanceU.FLOWUSDT.perp":{"status":"LONG","anti_order_sent":false,"pos":289.9,"triggered":"","up":0.347,"dn":0.345,"long_enter":"","high_since_long":"","short_enter":0.345,"low_since_short":0.341,"bar_n":1,"bar_enter_n":0,"ep":0.344,"af":0.02,"sar":0.362,"stoploss_price":0.358,"fee":2.468,"quote_ccy":-88.2,"net_profit":8.77}}