{"BinanceU.1000SHIBUSDT.perp":{"status":"EMPTY","anti_order_sent":false,"pos":0,"real_pos":"","triggered":"","up":0.020355,"dn":0.017407,"long_enter":"","high_since_long":"","short_enter":"","low_since_short":"","bar_n":"","bar_enter_n":0,"ep":"","af":"","sar":"","stoploss_price":"","fee":402.536,"quote_ccy":104.45,"net_profit":-298.09},"BinanceU.ALPHAUSDT.perp":{"status":"EMPTY","anti_order_sent":false,"pos":0,"real_pos":"","triggered":"","up":0.153,"dn":0.1075,"long_enter":"","high_since_long":"","short_enter":"","low_since_short":"","bar_n":"","bar_enter_n":0,"ep":"","af":"","sar":"","stoploss_price":"","fee":72.851,"quote_ccy":222.18,"net_profit":149.33},"BinanceU.CTKUSDT.perp":{"status":"EMPTY","anti_order_sent":false,"pos":0,"real_pos":"","triggered":"","up":1.1406,"dn":0.9408,"long_enter":"","high_since_long":"","short_enter":"","low_since_short":"","bar_n":"","bar_enter_n":0,"ep":"","af":"","sar":"","stoploss_price":"","fee":39.731,"quote_ccy":1363.79,"net_profit":1324.06},"BinanceU.DYDXUSDT.perp":{"status":"EMPTY","anti_order_sent":false,"pos":0,"real_pos":"","triggered":"","up":1.428,"dn":1.09,"long_enter":"","high_since_long":"","short_enter":"","low_since_short":"","bar_n":"","bar_enter_n":0,"ep":"","af":"","sar":"","stoploss_price":"","fee":73.181,"quote_ccy":-672.83,"net_profit":-746.01},"BinanceU.GRTUSDT.perp":{"status":"EMPTY","anti_order_sent":false,"pos":0,"real_pos":"","triggered":"","up":0.38037,"dn":0.30147,"long_enter":"","high_since_long":"","short_enter":"","low_since_short":"","bar_n":"","bar_enter_n":0,"ep":"","af":"","sar":"","stoploss_price":"","fee":149.073,"quote_ccy":3460.11,"net_profit":3311.04},"BinanceU.MKRUSDT.perp":{"status":"EMPTY","anti_order_sent":false,"pos":0,"real_pos":"","triggered":"","up":2476,"dn":1840.4,"long_enter":"","high_since_long":"","short_enter":"","low_since_short":"","bar_n":"","bar_enter_n":0,"ep":"","af":"","sar":"","stoploss_price":"","fee":79.55,"quote_ccy":-362.4,"net_profit":-441.95},"BinanceU.MTLUSDT.perp":{"status":"EMPTY","anti_order_sent":false,"pos":0,"real_pos":"","triggered":"","up":1.832,"dn":1.5216,"long_enter":"","high_since_long":"","short_enter":"","low_since_short":"","bar_n":"","bar_enter_n":0,"ep":"","af":"","sar":"","stoploss_price":"","fee":956.704,"quote_ccy":4686.38,"net_profit":3729.68},"BinanceU.SANDUSDT.perp":{"status":"EMPTY","anti_order_sent":false,"pos":0,"real_pos":"","triggered":"","up":1.1885,"dn":0.6261,"long_enter":"","high_since_long":"","short_enter":"","low_since_short":"","bar_n":"","bar_enter_n":0,"ep":"","af":"","sar":"","stoploss_price":"","fee":57.747,"quote_ccy":270.77,"net_profit":213.02},"BinanceU.XRPUSDT.perp":{"status":"EMPTY","anti_order_sent":false,"pos":0,"real_pos":"","triggered":"","up":0.5108,"dn":0.4888,"long_enter":"","high_since_long":"","short_enter":"","low_since_short":"","bar_n":"","bar_enter_n":0,"ep":"","af":"","sar":"","stoploss_price":"","fee":0.84,"quote_ccy":-37.42,"net_profit":-38.26},"BinanceU.HOTUSDT.perp":{"status":"EMPTY","anti_order_sent":false,"pos":0,"real_pos":"","triggered":"","up":0.004234,"dn":0.003582,"long_enter":"","high_since_long":"","short_enter":"","low_since_short":"","bar_n":"","bar_enter_n":0,"ep":"","af":"","sar":"","stoploss_price":"","fee":118.772,"quote_ccy":1656.66,"net_profit":1537.89},"BinanceU.QTUMUSDT.perp":{"status":"EMPTY","anti_order_sent":false,"pos":0,"triggered":"","up":6.49,"dn":3.322,"long_enter":"","high_since_long":"","short_enter":"","low_since_short":"","bar_n":"","bar_enter_n":0,"ep":"","af":"","sar":"","stoploss_price":"","fee":70.519,"quote_ccy":-695.19,"net_profit":-765.71},"BinanceU.ATOMUSDT.perp":{"status":"EMPTY","anti_order_sent":false,"pos":0,"triggered":"","up":11.713,"dn":8.745,"long_enter":"","high_since_long":"","short_enter":"","low_since_short":"","bar_n":"","bar_enter_n":0,"ep":"","af":"","sar":"","stoploss_price":"","fee":71.4,"quote_ccy":510.03,"net_profit":438.63},"BinanceU.SKLUSDT.perp":{"status":"EMPTY","anti_order_sent":false,"pos":0,"triggered":"","up":0.08997,"dn":0.07221,"long_enter":"","high_since_long":"","short_enter":"","low_since_short":"","bar_n":"","bar_enter_n":0,"ep":"","af":"","sar":"","stoploss_price":"","fee":77.535,"quote_ccy":745.97,"net_profit":668.44},"BinanceU.BALUSDT.perp":{"status":"EMPTY","anti_order_sent":false,"pos":0,"triggered":"","up":4.693,"dn":2.805,"long_enter":"","high_since_long":"","short_enter":"","low_since_short":"","bar_n":"","bar_enter_n":0,"ep":"","af":"","sar":"","stoploss_price":"","fee":0,"quote_ccy":0,"net_profit":0},"BinanceU.KAVAUSDT.perp":{"status":"EMPTY","anti_order_sent":false,"pos":0,"triggered":"","up":0.8106,"dn":0.6348,"long_enter":"","high_since_long":"","short_enter":"","low_since_short":"","bar_n":"","bar_enter_n":0,"ep":"","af":"","sar":"","stoploss_price":"","fee":3.629,"quote_ccy":175.11,"net_profit":171.48},"BinanceU.RSRUSDT.perp":{"status":"EMPTY","anti_order_sent":false,"pos":0,"triggered":"","up":0.027476,"dn":0.008009,"long_enter":"","high_since_long":"","short_enter":"","low_since_short":"","bar_n":"","bar_enter_n":0,"ep":"","af":"","sar":"","stoploss_price":"","fee":1.845,"quote_ccy":-200.21,"net_profit":-202.05},"BinanceU.SOLUSDT.perp":{"status":"EMPTY","anti_order_sent":false,"pos":0,"triggered":"","up":260.39,"dn":223.99,"long_enter":"","high_since_long":"","short_enter":"","low_since_short":"","bar_n":"","bar_enter_n":0,"ep":"","af":"","sar":"","stoploss_price":"","fee":0.431,"quote_ccy":-36.9,"net_profit":-37.33},"BinanceU.VETUSDT.perp":{"status":"EMPTY","anti_order_sent":false,"pos":0,"triggered":"","up":0.08387,"dn":0.04738,"long_enter":"","high_since_long":"","short_enter":"","low_since_short":"","bar_n":"","bar_enter_n":0,"ep":"","af":"","sar":"","stoploss_price":"","fee":3.287,"quote_ccy":37.25,"net_profit":33.96},"BinanceU.XMRUSDT.perp":{"status":"EMPTY","anti_order_sent":false,"pos":0,"triggered":"","up":216.41,"dn":181.11,"long_enter":"","high_since_long":"","short_enter":"","low_since_short":"","bar_n":"","bar_enter_n":0,"ep":"","af":"","sar":"","stoploss_price":"","fee":25.433,"quote_ccy":262.62,"net_profit":237.19}}